fcx_playground/__init__.py
fcx_playground/fcx_cesium_viz/__init__.py
fcx_playground/fcx_cesium_viz/base_viz.py
fcx_playground/fcx_cesium_viz/czml_viz.py
fcx_playground/fcx_cesium_viz/tiles_viz.py
fcx_playground/fcx_dataprocess/__init__.py
fcx_playground/fcx_dataprocess/czml_nav.py
fcx_playground/fcx_dataprocess/tiles_rad_range.py
fcx_playground/fcx_dataprocess/abstract/__init__.py
fcx_playground/fcx_dataprocess/abstract/czml_data_process.py
fcx_playground/fcx_dataprocess/abstract/data_process.py
fcx_playground/fcx_dataprocess/abstract/tiles_pointcloud_data_process.py
fcx_playground/fcx_dataprocess/utils/__init__.py
fcx_playground/fcx_dataprocess/utils/czml_model.py
fcx_playground/fcx_dataprocess/utils/czml_writer_nav.py
fcx_playground/fcx_dataprocess/utils/tiles_model.py
fcx_playground/fcx_dataprocess/utils/tiles_point_cloud.py
fcx_playground/fcx_dataprocess/utils/tiles_writer.py
fcx_playground-1.0.2.dist-info/METADATA
fcx_playground-1.0.2.dist-info/WHEEL
fcx_playground-1.0.2.dist-info/licenses/LICENCE
fcx_playground-1.0.2.dist-info/RECORD
