Metadata-Version: 2.1
Name: fcx_playground
Version: 1.0.2
Summary: A package that has a core fcx data processing module and a module to visualize the processed data in python interactive notebook environment (playground).
Project-URL: Homepage, https://github.com/ghrcdaac/fcx-playground-backend
Project-URL: Bug Tracker, https://github.com/ghrcdaac/fcx-playground-backend/issues
Author-email: sanzog03 <sanzog03@gmail.com>
License-File: LICENCE
Classifier: License :: OSI Approved :: MIT License
Classifier: Operating System :: OS Independent
Classifier: Programming Language :: Python :: 3
Requires-Python: >=3.7
Requires-Dist: boto3
Requires-Dist: netcdf4
Requires-Dist: numpy
Requires-Dist: pandas
Requires-Dist: xarray
Requires-Dist: zarr
